[
  {
    "row_id": "6b77d2cddd91a74a",
    "rank": 1,
    "system": "FASSONERIA 4.0",
    "product": "NQ",
    "developer": "KORIAL SYSTEMS",
    "pnl": 993.33,
    "current_position": "Flat",
    "nearest_order": "--"
  },
  {
    "row_id": "5efb236c16f2b2bb",
    "rank": 2,
    "system": "Position Trad Cont v.5.2 _ Live Cattle LE",
    "product": "LE",
    "developer": "AutoTradingBot",
    "pnl": 440.0,
    "current_position": "Long 1 @ 244.80",
    "nearest_order": "Sell STP 1 @ 243.05"
  },
  {
    "row_id": "291d7e1c4629fcf8",
    "rank": 3,
    "system": "Ackbar Kgor SwissFranc Medses",
    "product": "SF",
    "developer": "ILernet Trading Systems",
    "pnl": 175.0,
    "current_position": "Long 1 @ 1.2844",
    "nearest_order": "Sell STP 1 @ 1.2763"
  },
  {
    "row_id": "40c35bca9c30d6a9",
    "rank": 4,
    "system": "Sucellus E-mini DowJones 5'",
    "product": "YM",
    "developer": "0MG SYST3MS",
    "pnl": 50.0,
    "current_position": "Flat",
    "nearest_order": "--"
  },
  {
    "row_id": "ec106baa83c420ea",
    "rank": 5,
    "system": "Watto Corn 3Loops",
    "product": "ZC",
    "developer": "ILernet Trading Systems",
    "pnl": -37.5,
    "current_position": "Short 1 @ 470",
    "nearest_order": "Buy STP 1 @ 478.75"
  },
  {
    "row_id": "ced97469e0ffca29",
    "rank": 6,
    "system": "CONES BRITISH YM LUDOVIC",
    "product": "BP",
    "developer": "CirusTrading",
    "pnl": -37.5,
    "current_position": "Long 1 @ 1.3531",
    "nearest_order": "--"
  },
  {
    "row_id": "2c8c22117100f8f2",
    "rank": 7,
    "system": "CIRUS ST EUROFX NEBULA",
    "product": "URO",
    "developer": "CirusTrading",
    "pnl": -75.0,
    "current_position": "Long 1 @ 1.1826",
    "nearest_order": "--"
  },
  {
    "row_id": "4a25a57409ea6391",
    "rank": 8,
    "system": "CIRUS EURFX ST13 ROGY",
    "product": "URO",
    "developer": "CirusTrading",
    "pnl": -75.0,
    "current_position": "Long 1 @ 1.1560",
    "nearest_order": "--"
  },
  {
    "row_id": "f976c1609f4ee87c",
    "rank": 9,
    "system": "CONES TNOTE SWISS 90 90",
    "product": "ZN",
    "developer": "CirusTrading",
    "pnl": -93.75,
    "current_position": "Long 1 @ 111.29690",
    "nearest_order": "--"
  },
  {
    "row_id": "94a55f22903f34e7",
    "rank": 10,
    "system": "Watto Kgor Wheat Medses",
    "product": "ZW",
    "developer": "ILernet Trading Systems",
    "pnl": -150.0,
    "current_position": "Short 1 @ 637.75",
    "nearest_order": "Buy LMT 1 @ 560.50"
  }
]